comic_dl/__init__.py
comic_dl/core/__init__.py
comic_dl/core/comic.py
comic_dl/core/commands.py
comic_dl/core/config.py
comic_dl/core/downloader.py
comic_dl/core/handlers.py
comic_dl/utils/__init__.py
comic_dl/utils/db.py
comic_dl/utils/driver.py
comic_dl/utils/exceptions.py
comic_dl/utils/helpers.py
comicdl-0.1.4.dist-info/LICENSE
comicdl-0.1.4.dist-info/METADATA
comicdl-0.1.4.dist-info/WHEEL
comicdl-0.1.4.dist-info/entry_points.txt
comicdl-0.1.4.dist-info/top_level.txt
comicdl-0.1.4.dist-info/RECORD
