Metadata-Version: 2.1
Name: comicdl
Version: 0.1.4
Summary: A cli comic downloader.
Home-page: http://github.com/oluwafenyi/comic-dl/
Author: oluwafenyi
Author-email: o.enyioma@gmail.com
License: MIT
Keywords: comics comic download cli
Platform: UNKNOWN
Classifier: Development Status :: 3 - Alpha
Classifier: Programming Language :: Python :: 3
Classifier: License :: OSI Approved :: MIT License
Classifier: Operating System :: Microsoft :: Windows
Classifier: Operating System :: POSIX :: Linux
Requires-Python: >3.5
Requires-Dist: requests (==2.22.0)
Requires-Dist: selenium (==3.141.0)
Requires-Dist: tqdm (==4.40.0)
Requires-Dist: appdirs (==1.4.3)
